[
     {
      "car_id" : 1,
      "car_type" : "sedan",
      "car_model" : "Suzuki Swift",
      "car_color" : "white",
      "owners": [
        {
          "owner_id" : 1,
          "owner_name" : "Ivan",
          "owner_phone" : "+38012345678"
        }
      ]
    },
    {
     "car_id" : 2,
     "car_type" : "hydbrid/electric",
     "car_model" : "Toyota Prius",
     "car_color" : "blue",
     "owners": [
        {
        "owner_id" : 2,
        "owner_name" : "Anton",
        "owner_phone" : "+38012345678"
        }
      ]
    },
    {
     "car_id" : 3,
     "car_type" : "wagon",
     "car_model" : "Ford Focus",
     "car_color" : "black",
     "owners": [
        {
        "owner_id" : 3,
        "owner_name" : "Stepan",
        "owner_phone" : "+38012345678"
        }
      ]
    }
]
